rohith/__init__.py
rohith/cli.py
rohith-0.1.3.dist-info/licenses/LICENSE
rohith-0.1.3.dist-info/METADATA
rohith-0.1.3.dist-info/WHEEL
rohith-0.1.3.dist-info/entry_points.txt
rohith-0.1.3.dist-info/top_level.txt
rohith-0.1.3.dist-info/RECORD
