Metadata-Version: 2.4
Name: rohith
Version: 0.1.3
Summary: A terminal-based CLI card to showcase Rohith Gowda's profile and quick contact tools.
Home-page: https://github.com/rohithgowdax/cli-card
Author: Rohith Gowda R
Classifier: Programming Language :: Python :: 3
Classifier: License :: OSI Approved :: MIT License
License-File: LICENSE
Requires-Dist: questionary
Requires-Dist: rich
Requires-Dist: requests
Dynamic: author
Dynamic: classifier
Dynamic: description
Dynamic: description-content-type
Dynamic: home-page
Dynamic: license-file
Dynamic: requires-dist
Dynamic: summary
